.hgignore
LICENSE
Makefile
distribute_setup.py
setup.py
lcdui/__init__.py
lcdui/common.py
lcdui/util.py
lcdui/core/__init__.py
lcdui/core/crc16.py
lcdui/core/cstruct.py
lcdui/devices/CrystalFontz.py
lcdui/devices/Generic.py
lcdui/devices/Interfaces.py
lcdui/devices/MatrixOrbital.py
lcdui/devices/__init__.py
lcdui/examples/sampleui.py
lcdui/ui/__init__.py
lcdui/ui/frame.py
lcdui/ui/ui.py
lcdui/ui/widget.py
pylcdui.egg-info/PKG-INFO
pylcdui.egg-info/SOURCES.txt
pylcdui.egg-info/dependency_links.txt
pylcdui.egg-info/top_level.txt