Metadata-Version: 1.0
Name: pylcdui
Version: 0.5.8
Summary: Library for CrystalFontz and Matrix-Orbital LCD displays
Home-page: http://code.google.com/p/pylcdui/
Author: mike wakerly
Author-email: opensource@hoho.com
License: UNKNOWN
Platform: UNKNOWN
